fms_mo/__init__.py
fms_mo/_version.py
fms_mo/calib.py
fms_mo/dq.py
fms_mo/prep.py
fms_mo/run_quant.py
fms_mo/training_args.py
fms_mo/version.py
fms_mo/aiu_addons/__init__.py
fms_mo/aiu_addons/fp8/__init__.py
fms_mo/aiu_addons/fp8/fp8_adapter.py
fms_mo/aiu_addons/fp8/fp8_attn.py
fms_mo/aiu_addons/fp8/fp8_linear.py
fms_mo/aiu_addons/fp8/fp8_spyre_op.py
fms_mo/aiu_addons/fp8/fp8_utils.py
fms_mo/aiu_addons/gptq/__init__.py
fms_mo/aiu_addons/gptq/gptq_aiu_adapter.py
fms_mo/aiu_addons/gptq/gptq_aiu_linear.py
fms_mo/aiu_addons/gptq/gptq_aiu_op.py
fms_mo/aiu_addons/i8i8/__init__.py
fms_mo/aiu_addons/i8i8/i8i8_aiu_adapter.py
fms_mo/aiu_addons/i8i8/i8i8_aiu_linear.py
fms_mo/aiu_addons/i8i8/i8i8_aiu_op.py
fms_mo/custom_ext_kernels/__init__.py
fms_mo/custom_ext_kernels/cutlass_i8i32gemm.cpp
fms_mo/custom_ext_kernels/cutlass_i8i32gemm.cu
fms_mo/custom_ext_kernels/ext_kernel_cublas.cpp
fms_mo/custom_ext_kernels/triton_kernels.py
fms_mo/custom_ext_kernels/utils.py
fms_mo/fx/__init__.py
fms_mo/fx/dynamo_utils.py
fms_mo/fx/utils.py
fms_mo/modules/__init__.py
fms_mo/modules/bmm.py
fms_mo/modules/conv.py
fms_mo/modules/linear.py
fms_mo/modules/lstm.py
fms_mo/quant/README.md
fms_mo/quant/ptq.py
fms_mo/quant/quantizers.py
fms_mo/quant_refactor/base_model.py
fms_mo/quant_refactor/base_quant.py
fms_mo/quant_refactor/get_quantizer_rc.py
fms_mo/quant_refactor/linear_utils.py
fms_mo/quant_refactor/lsq_rc.py
fms_mo/quant_refactor/pact2_rc.py
fms_mo/quant_refactor/pact2sym_rc.py
fms_mo/quant_refactor/pact_rc.py
fms_mo/quant_refactor/pactplussym_rc.py
fms_mo/quant_refactor/per_channel_ste.py
fms_mo/quant_refactor/per_tensor_ste.py
fms_mo/quant_refactor/qmax_rc.py
fms_mo/quant_refactor/quantizers_new.py
fms_mo/quant_refactor/sawb_rc.py
fms_mo/quant_refactor/sawb_utils.py
fms_mo/quant_refactor/torch_quantizer.py
fms_mo/recipes/dq.json
fms_mo/recipes/ptq_int8.json
fms_mo/recipes/qat_int8.json
fms_mo/utils/README.md
fms_mo/utils/__init__.py
fms_mo/utils/aiu_utils.py
fms_mo/utils/calib_data.py
fms_model_optimizer-0.8.0.dist-info/licenses/LICENSE
fms_model_optimizer-0.8.0.dist-info/METADATA
fms_model_optimizer-0.8.0.dist-info/WHEEL
fms_model_optimizer-0.8.0.dist-info/top_level.txt
fms_model_optimizer-0.8.0.dist-info/RECORD
