Metadata-Version: 2.4
Name: fms-model-optimizer
Version: 0.8.0
Summary: Quantization Techniques
License: Apache-2.0
Project-URL: homepage, https://github.com/foundation-model-stack/fms-model-optimizer
Project-URL: source, https://github.com/foundation-model-stack/fms-model-optimizer
Project-URL: issues, https://github.com/foundation-model-stack/fms-model-optimizer/issues
Classifier: Development Status :: 3 - Alpha
Classifier: License :: OSI Approved :: Apache Software License
Classifier: License :: OSI Approved :: MIT License
Classifier: Operating System :: POSIX :: Linux
Classifier: Topic :: Scientific/Engineering :: Artificial Intelligence
Classifier: Programming Language :: Python :: 3
Classifier: Programming Language :: Python :: 3.10
Classifier: Programming Language :: Python :: 3.11
Classifier: Programming Language :: Python :: 3.12
Classifier: Programming Language :: Python :: Implementation :: CPython
Requires-Python: <3.13,>3.9
License-File: LICENSE
Requires-Dist: numpy<2.3.0,>=1.26.4
Requires-Dist: accelerate!=0.34,<1.11,>=0.20.3
Requires-Dist: transformers<4.58,>=4.45
Requires-Dist: torch<2.10.0,>=2.2.0
Requires-Dist: tqdm<5.0,>=4.66.2
Requires-Dist: datasets<5.0,>=3.0.0
Requires-Dist: pandas
Requires-Dist: safetensors
Requires-Dist: pkginfo>1.10
Provides-Extra: examples
Requires-Dist: ninja<2.0,>=1.11.1.1; extra == "examples"
Requires-Dist: evaluate; extra == "examples"
Requires-Dist: huggingface_hub; extra == "examples"
Provides-Extra: fp8
Requires-Dist: llmcompressor; extra == "fp8"
Requires-Dist: torchao==0.11; extra == "fp8"
Provides-Extra: gptq
Requires-Dist: Cython; extra == "gptq"
Requires-Dist: gptqmodel>=1.7.3; extra == "gptq"
Provides-Extra: mx
Requires-Dist: microxcaling>=1.1; extra == "mx"
Provides-Extra: opt
Requires-Dist: fms-model-optimizer[fp8,gptq,mx]; extra == "opt"
Provides-Extra: aiu
Requires-Dist: ibm-fms>=0.0.8; extra == "aiu"
Provides-Extra: torchvision
Requires-Dist: torchvision>=0.17; extra == "torchvision"
Provides-Extra: flash-attn
Requires-Dist: flash-attn<3.0,>=2.5.3; extra == "flash-attn"
Provides-Extra: triton
Requires-Dist: triton<3.5,>=3.0; extra == "triton"
Provides-Extra: visualize
Requires-Dist: matplotlib; extra == "visualize"
Requires-Dist: graphviz; extra == "visualize"
Requires-Dist: pygraphviz; extra == "visualize"
Requires-Dist: tensorboard; extra == "visualize"
Requires-Dist: notebook; extra == "visualize"
Provides-Extra: dev
Requires-Dist: pre-commit<5.0,>=3.0.4; extra == "dev"
Provides-Extra: test
Requires-Dist: pytest; extra == "test"
Requires-Dist: pillow; extra == "test"
Dynamic: license-file
